lamestation/__init__.py
lamestation/_version.py
lamestation/freqtable.py
lamestation-0.10.6.dist-info/licenses/LICENSE
lamestation-0.10.6.dist-info/METADATA
lamestation-0.10.6.dist-info/WHEEL
lamestation-0.10.6.dist-info/top_level.txt
lamestation-0.10.6.dist-info/RECORD
