Metadata-Version: 2.4
Name: lamestation
Version: 0.10.6
Summary: LameStation SDK.
License: GPL-3.0-or-later
Project-URL: Home, https://gitlab.com/lamestation/sdk
Project-URL: Issues, https://gitlab.com/lamestation/sdk/-/issues
Classifier: Development Status :: 2 - Pre-Alpha
Classifier: Intended Audience :: Developers
Classifier: Programming Language :: Python :: 3
Classifier: Programming Language :: Python :: 3.9
Classifier: Programming Language :: Python :: 3.10
Classifier: Programming Language :: Python :: 3.11
Classifier: Programming Language :: Python :: 3.12
Classifier: Programming Language :: Python :: 3.13
Requires-Python: >=3.9
License-File: LICENSE
Dynamic: license-file
